myctypes/__init__.py
myctypes/constants.py
myctypes/structured_data.py
myctypes-0.1.0.dist-info/LICENSE
myctypes-0.1.0.dist-info/WHEEL
myctypes-0.1.0.dist-info/METADATA
myctypes-0.1.0.dist-info/RECORD
