Metadata-Version: 2.1
Name: myctypes
Version: 0.1.0
Summary: Attempts to make a slightly nicer interface to ctypes
Author: Zachary Farquharson
Author-email: PercyJackson235@gmail.com
Requires-Python: >=3.7,<4.0
Classifier: Programming Language :: Python :: 3
Classifier: Programming Language :: Python :: 3.10
Classifier: Programming Language :: Python :: 3.7
Classifier: Programming Language :: Python :: 3.8
Classifier: Programming Language :: Python :: 3.9
